cellmerge/__init__.py
cellmerge/cellmerge.py
cellmerge-0.1.1.dist-info/METADATA
cellmerge-0.1.1.dist-info/WHEEL
cellmerge-0.1.1.dist-info/entry_points.txt
cellmerge-0.1.1.dist-info/top_level.txt
cellmerge-0.1.1.dist-info/RECORD
