Metadata-Version: 2.2
Name: cellmerge
Version: 0.1.1
Summary: Merge nuclei segmentations from multiple models
Home-page: https://github.com/jagadhesh89/MergeSegmentations/tree/main/cellmerge
Author: Jag Balan
Author-email: balan.jagadheshwar@mayo.edu
Classifier: Programming Language :: Python :: 3
Classifier: License :: OSI Approved :: MIT License
Classifier: Operating System :: OS Independent
Requires-Python: >=3.6
Requires-Dist: tiatoolbox>=1.4.0
Requires-Dist: numpy>=1.23.5
Requires-Dist: annoy>=1.17.3
Requires-Dist: matplotlib>=3.6.2
Dynamic: author
Dynamic: author-email
Dynamic: classifier
Dynamic: description
Dynamic: description-content-type
Dynamic: home-page
Dynamic: requires-dist
Dynamic: requires-python
Dynamic: summary
